mkv_episode_matcher_vob/.gitattributes
mkv_episode_matcher_vob/__init__.py
mkv_episode_matcher_vob/__main__.py
mkv_episode_matcher_vob/config.py
mkv_episode_matcher_vob/episode_matcher.py
mkv_episode_matcher_vob/mkv_to_srt.py
mkv_episode_matcher_vob/requirements.txt
mkv_episode_matcher_vob/tmdb_client.py
mkv_episode_matcher_vob/utils.py
mkv_episode_matcher_vob/libraries/pgs2srt/.gitignore
mkv_episode_matcher_vob/libraries/pgs2srt/README.md
mkv_episode_matcher_vob/libraries/pgs2srt/__init__.py
mkv_episode_matcher_vob/libraries/pgs2srt/imagemaker.py
mkv_episode_matcher_vob/libraries/pgs2srt/pgs2srt.py
mkv_episode_matcher_vob/libraries/pgs2srt/pgsreader.py
mkv_episode_matcher_vob/libraries/pgs2srt/requirements.txt
mkv_episode_matcher_vob/libraries/pgs2srt/Libraries/SubZero/SubZero.py
mkv_episode_matcher_vob/libraries/pgs2srt/Libraries/SubZero/post_processing.py
mkv_episode_matcher_vob/libraries/pgs2srt/Libraries/SubZero/dictionaries/data.py
mkv_episode_matcher_vob/notebooks/get_subtitles_test.ipynb
mkv_episode_matcher_vob-0.1.5.1.dist-info/METADATA
mkv_episode_matcher_vob-0.1.5.1.dist-info/WHEEL
mkv_episode_matcher_vob-0.1.5.1.dist-info/entry_points.txt
mkv_episode_matcher_vob-0.1.5.1.dist-info/top_level.txt
mkv_episode_matcher_vob-0.1.5.1.dist-info/RECORD
