Metadata-Version: 2.1
Name: mkv-episode-matcher-vob
Version: 0.1.5.1
Summary: The MKV Episode Matcher VOB is a fork of MKV Episode Matcher for identifying TV series episodes from MKV files and renaming the files accordingly with additional support for VOB files.
Home-page: https://github.com/NiklasPrahl/mkv-episode-matcher-vob
Author: Niklas Prahl (credits to: Jonathan Sakkos, mkv_episode_matcher)
Author-email: NiklasPrahl <niklas.prahl-git@gmx.net>
License: MIT
Project-URL: Documentation, https://github.com/Jsakkos/mkv-episode-matcher-vob#readme
Project-URL: Issues, https://github.com/Jsakkos/mkv-episode-matcher-vob/issues
Project-URL: Source, https://github.com/Jsakkos/mkv-episode-matcher-vob
Classifier: Development Status :: 4 - Beta
Classifier: Programming Language :: Python
Classifier: Programming Language :: Python :: 3.8
Classifier: Programming Language :: Python :: 3.9
Classifier: Programming Language :: Python :: 3.10
Classifier: Programming Language :: Python :: 3.11
Classifier: Programming Language :: Python :: 3.12
Classifier: Programming Language :: Python :: Implementation :: CPython
Classifier: Programming Language :: Python :: Implementation :: PyPy
Requires-Python: >=3.8
Requires-Dist: requests
Requires-Dist: loguru
Requires-Dist: pillow
Requires-Dist: configparser
Requires-Dist: tmdb-client
Requires-Dist: pytesseract
Requires-Dist: opensubtitlescom
